nasa_scrub-3.0.dist-info/licenses/LICENSE
scrub/__init__.py
scrub/scrub_cli.py
scrub/scrubme.py
scrub/targets/__init__.py
scrub/targets/collaborator/__init__.py
scrub/targets/collaborator/do_collaborator.py
scrub/targets/scrub_gui/__init__.py
scrub/targets/scrub_gui/do_scrub_gui.py
scrub/tools/__init__.py
scrub/tools/parsers/__init__.py
scrub/tools/parsers/csv_parser.py
scrub/tools/parsers/get_codesonar_warnings.py
scrub/tools/parsers/get_coverity_warnings.py
scrub/tools/parsers/get_gbuild_warnings.py
scrub/tools/parsers/get_gcc_warnings.py
scrub/tools/parsers/get_javac_warnings.py
scrub/tools/parsers/get_pylint_warnings.py
scrub/tools/parsers/get_sonarqube_warnings.py
scrub/tools/parsers/parse_metrics.py
scrub/tools/parsers/translate_results.py
scrub/tools/templates/codeql.template
scrub/tools/templates/codesonar.template
scrub/tools/templates/coverity.template
scrub/tools/templates/gbuild.template
scrub/tools/templates/gcc.template
scrub/tools/templates/javac.template
scrub/tools/templates/pylint.template
scrub/tools/templates/sonarqube.template
scrub/utils/__init__.py
scrub/utils/diff_results.py
scrub/utils/do_clean.py
scrub/utils/scrub_defaults.cfg
scrub/utils/scrub_utilities.py
scrub/utils/filtering/FilteringDefaults
scrub/utils/filtering/__init__.py
scrub/utils/filtering/create_file_list.py
scrub/utils/filtering/do_filtering.py
scrub/utils/filtering/filter_results.py
nasa_scrub-3.0.dist-info/METADATA
nasa_scrub-3.0.dist-info/WHEEL
nasa_scrub-3.0.dist-info/entry_points.txt
nasa_scrub-3.0.dist-info/top_level.txt
nasa_scrub-3.0.dist-info/RECORD
