Metadata-Version: 2.4
Name: nasa-scrub
Version: 3.0
Summary: SCRUB is an orchestration and aggregation tool for static code analysis tools.
Home-page: https://github.com/nasa/scrub
Author: Lyle Barner
Author-email: lyle.barner@jpl.nasa.gov
License: Apache License 2.0
Project-URL: Bug Tracker, https://github.com/nasa/scrub/issues
Project-URL: Documentation, https://nasa.github.io/scrub
Project-URL: Source, https://github.com/nasa/scrub
Keywords: scrub
Classifier: Development Status :: 5 - Production/Stable
Classifier: Intended Audience :: Developers
Classifier: Natural Language :: English
Classifier: Programming Language :: Python :: 3
Classifier: License :: OSI Approved :: Apache Software License
License-File: LICENSE
Requires-Dist: sarif-tools
Dynamic: license-file
